setup.py
giki/__init__.py
giki/cli.py
giki/core.py
giki/formatter.py
giki/web.py
giki.egg-info/PKG-INFO
giki.egg-info/SOURCES.txt
giki.egg-info/dependency_links.txt
giki.egg-info/entry_points.txt
giki.egg-info/requires.txt
giki.egg-info/top_level.txt
test/test_core.py
test/test_formatter.py