Metadata-Version: 1.0
Name: giki
Version: 0.1pre
Summary: a Git-based wiki
Home-page: UNKNOWN
Author: Adam Brenecki
Author-email: adam@brenecki.id.au
License: UNKNOWN
Platform: UNKNOWN
